{
    "alunos":[
        {
        "id": "1",
        "nome": "Diogo Moreira",
        "idade": 27,
        "nomeCurso": ["Academia do Flutter", "Imersao Getx"],
        "cursos": [
            {
                "id": 1,
                "nome": "Academia do flutter",
                "isAluno": true
            },
            {
                "id": 2,
                "nome": "Imersao Getx",
                "isAluno": false
            }
        ],
        "endereço":{
            "rua": "Rua X",
            "numero": 300,
            "CEP": "0900090802",
            "cidade": {
                "id": 1,
                "nome": "Monte Alegre do sul"
            },
            "telefone":{
                "ddd":11,
                "telefone": "928985333"
            }
        }
        },
        {
            "id": "2",
            "nome": "Joyce Costa",
            "idade": 26,
            "nomeCurso": ["Academia do Flutter", "Imersao Getx"],
            "cursos": [
                {
                    "id": 1,
                    "nome": "Academia do flutter",
                    "isAluno": true
                },
                {
                    "id": 2,
                    "nome": "Imersao Getx",
                    "isAluno": true
                }
            ],
            "endereço":{
                "rua": "Rua X",
                "numero": 300,
                "CEP": "0900090802",
                "cidade": {
                    "id": 1,
                    "nome": "Monte Alegre do sul"
                },
                "telefone":{
                    "ddd":11,
                    "telefone": "928985333"
                }
            }
            }
    ]
}
